image_lowpass_filters/__init__.py
image_lowpass_filters/filters.py
image_lowpass_filters/selective.py
image_lowpass_filters-0.1.2.dist-info/licenses/LICENSE
image_lowpass_filters-0.1.2.dist-info/METADATA
image_lowpass_filters-0.1.2.dist-info/WHEEL
image_lowpass_filters-0.1.2.dist-info/top_level.txt
image_lowpass_filters-0.1.2.dist-info/RECORD
