Metadata-Version: 2.4
Name: image-lowpass-filters
Version: 0.1.2
Summary: Ideal, Butterworth and Gaussian frequency‐domain filters for PyTorch
Home-page: https://github.com/CassiniHuy/image-low-pass-filters-pytorch
Author: Cassini Wei
Author-email: cassiniwei@outlook.com
License: MIT
Classifier: Programming Language :: Python :: 3
Classifier: Operating System :: OS Independent
Requires-Python: >=3.7
License-File: LICENSE
Requires-Dist: torch>=1.7.0
Dynamic: author
Dynamic: author-email
Dynamic: classifier
Dynamic: description
Dynamic: description-content-type
Dynamic: home-page
Dynamic: license
Dynamic: license-file
Dynamic: requires-dist
Dynamic: requires-python
Dynamic: summary
